compas_tna/__init__.py
compas_tna/numdata.py
compas_tna/diagrams/__init__.py
compas_tna/diagrams/diagram.py
compas_tna/diagrams/diagram_arch.py
compas_tna/diagrams/diagram_circular.py
compas_tna/diagrams/diagram_rectangular.py
compas_tna/diagrams/forcediagram.py
compas_tna/diagrams/formdiagram.py
compas_tna/envelope/__init__.py
compas_tna/envelope/brepenvelope.py
compas_tna/envelope/crossvault.py
compas_tna/envelope/dome.py
compas_tna/envelope/envelope.py
compas_tna/envelope/meshenvelope.py
compas_tna/envelope/parametricenvelope.py
compas_tna/envelope/pavillionvault.py
compas_tna/envelope/pointedvault.py
compas_tna/equilibrium/__init__.py
compas_tna/equilibrium/diagrams.py
compas_tna/equilibrium/horizontal.py
compas_tna/equilibrium/horizontal_numpy.py
compas_tna/equilibrium/parallelisation.py
compas_tna/equilibrium/parallelisation_numpy.py
compas_tna/equilibrium/relaxation.py
compas_tna/equilibrium/scale_numpy.py
compas_tna/equilibrium/vertical_numpy.py
compas_tna/loads/__init__.py
compas_tna/loads/loadupdater.py
compas_tna/loads/thickness.py
compas_tna/notebook/__init__.py
compas_tna/notebook/scene/__init__.py
compas_tna/notebook/scene/forceobject.py
compas_tna/notebook/scene/formobject.py
compas_tna/rhino/__init__.py
compas_tna/rhino/scene/__init__.py
compas_tna/rhino/scene/forceobject.py
compas_tna/rhino/scene/formobject.py
compas_tna/scene/__init__.py
compas_tna/scene/forceobject.py
compas_tna/scene/formobject.py
compas_tna-0.7.0.dist-info/licenses/LICENSE
compas_tna-0.7.0.dist-info/METADATA
compas_tna-0.7.0.dist-info/WHEEL
compas_tna-0.7.0.dist-info/top_level.txt
compas_tna-0.7.0.dist-info/RECORD
