Metadata-Version: 2.4
Name: compas_tna
Version: 0.7.0
Summary: Form Finding of compression-only funicular networks, with vertical loads, using Thrust Network Analysis.
Author: Tomás Méndez Echenagucia, Matthias Rippmann
Author-email: tom van mele <tom.v.mele@gmail.com>
License: MIT License
Project-URL: Homepage, https://blockresearchgroup.github.io/compas_tna
Project-URL: Documentation, https://blockresearchgroup.github.io/compas_tna
Project-URL: Repository, https://github.com/blockresearchgroup/compas_tna.git
Project-URL: Changelog, https://github.com/blockresearchgroup/compas_tna/blob/main/CHANGELOG.md
Keywords: form finding,compression-only,funicular network,vertical loads,thrust network analysis
Classifier: Development Status :: 4 - Beta
Classifier: Topic :: Scientific/Engineering
Classifier: Programming Language :: Python
Classifier: Programming Language :: Python :: 3
Classifier: Programming Language :: Python :: 3.9
Classifier: Programming Language :: Python :: 3.10
Classifier: Programming Language :: Python :: 3.11
Requires-Python: >=3.9
License-File: LICENSE
Requires-Dist: compas
Requires-Dist: compas_fd
Provides-Extra: dev
Requires-Dist: attrs>=17.4; extra == "dev"
Requires-Dist: black>=22.12.0; extra == "dev"
Requires-Dist: bump-my-version; extra == "dev"
Requires-Dist: compas_invocations2; extra == "dev"
Requires-Dist: compas_notebook; extra == "dev"
Requires-Dist: compas_viewer; extra == "dev"
Requires-Dist: invoke>=0.14; extra == "dev"
Requires-Dist: ruff; extra == "dev"
Requires-Dist: sphinx_compas2_theme; extra == "dev"
Requires-Dist: twine; extra == "dev"
Requires-Dist: wheel; extra == "dev"
Dynamic: license-file
